pony3d/__init__.py
pony3d/file_operations.py
pony3d/main.py
pony3d/mask_operations.py
pony3d/terminal_operations.py
pony3d-0.1.0.dist-info/LICENSE
pony3d-0.1.0.dist-info/METADATA
pony3d-0.1.0.dist-info/WHEEL
pony3d-0.1.0.dist-info/entry_points.txt
pony3d-0.1.0.dist-info/top_level.txt
pony3d-0.1.0.dist-info/RECORD
